qojpca/__init__.py
qojpca/__main__.py
qojpca/base.py
qojpca/cli.py
qojpca/experiment_0.py
qojpca/experiment_1.py
qojpca/extractFeatures.py
qojpca-0.1.9.dist-info/LICENSE
qojpca-0.1.9.dist-info/METADATA
qojpca-0.1.9.dist-info/WHEEL
qojpca-0.1.9.dist-info/entry_points.txt
qojpca-0.1.9.dist-info/top_level.txt
qojpca-0.1.9.dist-info/RECORD
